LICENSE
MANIFEST.in
README.rst
buildout.cfg
requirements.txt
setup.py
version.txt
bob/__init__.py
bob.db.ijbc.egg-info/PKG-INFO
bob.db.ijbc.egg-info/SOURCES.txt
bob.db.ijbc.egg-info/dependency_links.txt
bob.db.ijbc.egg-info/entry_points.txt
bob.db.ijbc.egg-info/not-zip-safe
bob.db.ijbc.egg-info/requires.txt
bob.db.ijbc.egg-info/top_level.txt
bob/db/__init__.py
bob/db/ijbc/__init__.py
bob/db/ijbc/driver.py
bob/db/ijbc/query.py
bob/db/ijbc/reader.py
bob/db/ijbc/test.py
doc/conf.py
doc/guide.rst
doc/index.rst
doc/py_api.rst
doc/img/favicon.ico
doc/img/logo.png