Metadata-Version: 1.1
Name: bob.db.ijbc
Version: 1.0.4
Summary: IJB-C Database Access API for Bob
Home-page: https://gitlab.idiap.ch/bob/bob.db.ijbb
Author: Manuel Gunther
Author-email: siebenkopf@googlemail.com
License: BSD
Platform: UNKNOWN
Classifier: Framework :: Bob
Classifier: Development Status :: 4 - Beta
Classifier: Intended Audience :: Developers
Classifier: License :: OSI Approved :: BSD License
Classifier: Natural Language :: English
Classifier: Programming Language :: Python
Classifier: Programming Language :: Python :: 3
Classifier: Topic :: Scientific/Engineering :: Artificial Intelligence
Classifier: Topic :: Database :: Front-Ends
